---
sidebar: auto
title: Java ä¸­æ‹¼æ¥å­—ç¬¦ä¸²çš„å‡ ç§æ–¹æ³•æ•ˆç‡å¯¹æ¯”
date: 2019-03-05 15:39
author: dong4j
tags:
- String
---

::: tip æ‰§è¡Œæ•ˆç‡
StringBuffer > StringBuilder > StringUtils.join > concat > +
:::

<!-- more -->

[ğŸ‘ˆ **ç›¸å…³é¢è¯•é¢˜**](./README.md#_54-ğŸ‘‰-string-å¯¹-çš„é‡è½½-å­—ç¬¦ä¸²æ‹¼æ¥çš„å‡ ç§æ–¹å¼å’ŒåŒºåˆ«)

å…ˆæ¥åšä¸€ä¸ªæµ‹è¯•

```java
@Before
public void init(){
    IntStream.range(0, 100000).forEach((index) -> {
        list.add("str" + index);
    });
}

@Test
public void test1() {
    String ss = "";
    StopWatch stopWatch = new StopWatch("å­—ç¬¦ä¸²æ‹¼æ¥æ•ˆç‡å¯¹æ¯”");
    stopWatch.start("+");
    for (String s : list) {
        ss += s;
    }
    stopWatch.stop();
    System.out.println(stopWatch.prettyPrint());

    stopWatch.start("concat");
    ss = "";
    for (String s : list) {
        ss=ss.concat(s);
    }
    stopWatch.stop();
    System.out.println(stopWatch.prettyPrint());

    stopWatch.start("StringBuilder");
    StringBuilder stringBuilder = new StringBuilder();
    for (String s : list) {
        stringBuilder.append(s);
    }
    stopWatch.stop();
    System.out.println(stopWatch.prettyPrint());

    stopWatch.start("join");
    StringUtils.join(list);
    stopWatch.stop();
    System.out.println(stopWatch.prettyPrint());

    stopWatch.start("StringBuffer");
    StringBuffer stringBuffer = new StringBuffer();
    for (String s : list) {
        stringBuffer.append(s);
    }
    stopWatch.stop();
    System.out.println(stopWatch.prettyPrint());
}
```

è¾“å‡º:

```java
StopWatch 'å­—ç¬¦ä¸²æ‹¼æ¥æ•ˆç‡å¯¹æ¯”': running time (millis) = 57700
-----------------------------------------
ms     %     Task name
-----------------------------------------
44915  078%  +
12758  022%  concat
00003  000%  StringBuilder
00016  000%  join
00008  000%  StringBuffer
```

ç»“è®º:

```
StringBuffer > StringBuilder > StringUtils.join > concat > +
```

## StringBuilder

æ¯æ¬¡å­—ç¬¦ä¸²æ‹¼æ¥éƒ½åªæ˜¯æ‰©å±•å†…éƒ¨ char æ•°ç»„ï¼Œåªç”Ÿäº§ä¸€ä¸ªæœ€ç»ˆçš„ stringï¼Œæ‰€ä»¥è¿™ç§æ•ˆç‡æœ€é«˜

```java
public AbstractStringBuilder append(String str) {
    if (str == null)
        return appendNull();
    int len = str.length();
    ensureCapacityInternal(count + len);
    str.getChars(0, len, value, count);
    count += len;
    return this;
}
```

## StringBuffer

ä¸ StringBuilder å”¯ä¸€çš„åŒºåˆ«å°±æ˜¯ä½¿ç”¨äº†åŒæ­¥æ–¹æ³•, æ‰€ä»¥åœ¨å•çº¿ç¨‹ä¸‹åŒºåˆ«å¹¶ä¸å¤§

```java
public synchronized StringBuffer append(String str) {
    toStringCache = null;
    super.append(str);
    return this;
}
```

## StringUtils.join

å†…éƒ¨è¿˜æ˜¯ç”¨çš„ StringBuilder, åªæ˜¯å¤šäº†å¾ˆå¤šåˆ¤æ–­, é€ æˆè€—æ—¶å¢åŠ 

```java
public static String join(final Object[] array, String separator, final int startIndex, final int endIndex) {
    if (array == null) {
        return null;
    }
    if (separator == null) {
        separator = EMPTY;
    }

    // endIndex - startIndex > 0:   Len = NofStrings *(len(firstString) + len(separator))
    //           (Assuming that all Strings are roughly equally long)
    final int noOfItems = endIndex - startIndex;
    if (noOfItems <= 0) {
        return EMPTY;
    }

    final StringBuilder buf = new StringBuilder(noOfItems * 16);

    for (int i = startIndex; i < endIndex; i++) {
        if (i > startIndex) {
            buf.append(separator);
        }
        if (array[i] != null) {
            buf.append(array[i]);
        }
    }
    return buf.toString();
}
```

## concat

æ¯æ¬¡éƒ½ä¼šç”Ÿæˆä¸€ä¸ªæ–°çš„å­—ç¬¦ä¸², æ‰€ä»¥æ•ˆç‡å¾ˆä½

```java
public String concat(String str) {
    int otherLen = str.length();
    if (otherLen == 0) {
        return this;
    }
    int len = value.length;
    char buf[] = Arrays.copyOf(value, len + otherLen);
    str.getChars(buf, len);
    return new String(buf, true);
}
```

## JDK å¯¹ String "+" çš„ä¼˜åŒ–

è®©æˆ‘ä»¬æ¥çœ‹ä¸‹é¢çš„ä»£ç 

```java
public static void main(String[] args) throws InterruptedException {
    List<String> list = new ArrayList<>();

    IntStream.range(0, 100000).forEach((index) -> {
        list.add("str" + index);
    });

    String ss = "";
    for (String s : list) {
        ss += s;
    }
    
    Thread.currentThread().join();
}
```

è¿™æ®µä»£ç åç¼–è¯‘å:

```java
public static void main(String[] args) throws InterruptedException {
    List<String> list = new ArrayList();
    IntStream.range(0, 100000).forEach((index) -> {
        list.add("str" + index);
    });
    String ss = "";

    String s;
    for(Iterator var3 = list.iterator(); var3.hasNext(); ss = ss + s) {
        s = (String)var3.next();
    }

    Thread.currentThread().join();
}
```

ä½¿ç”¨ `javap` æŸ¥çœ‹å­—èŠ‚ç 

```java
Compiled from "StringTest.java"
public class com.iflytek.test.common.StringTest {
  public com.iflytek.test.common.StringTest();
    Code:
       0: aload_0
       1: invokespecial #1                  // Method java/lang/Object."<init>":()V
       4: return

  public static void main(java.lang.String[]) throws java.lang.InterruptedException;
    Code:
       0: new           #2                  // class java/util/ArrayList
       3: dup
       4: invokespecial #3                  // Method java/util/ArrayList."<init>":()V
       7: astore_1
       8: iconst_0
       9: ldc           #4                  // int 100000
      11: invokestatic  #5                  // InterfaceMethod java/util/stream/IntStream.range:(II)Ljava/util/stream/IntStream;
      14: aload_1
      15: invokedynamic #6,  0              // InvokeDynamic #0:accept:(Ljava/util/List;)Ljava/util/function/IntConsumer;
      20: invokeinterface #7,  2            // InterfaceMethod java/util/stream/IntStream.forEach:(Ljava/util/function/IntConsumer;)V
      25: ldc           #8                  // String
      27: astore_2
      28: aload_1
      29: invokeinterface #9,  1            // InterfaceMethod java/util/List.iterator:()Ljava/util/Iterator;
      34: astore_3
      35: aload_3
      36: invokeinterface #10,  1           // InterfaceMethod java/util/Iterator.hasNext:()Z
      41: ifeq          78
      44: aload_3
      45: invokeinterface #11,  1           // InterfaceMethod java/util/Iterator.next:()Ljava/lang/Object;
      50: checkcast     #12                 // class java/lang/String
      53: astore        4
      55: new           #13                 // class java/lang/StringBuilder
      58: dup
      59: invokespecial #14                 // Method java/lang/StringBuilder."<init>":()V
      62: aload_2
      63: invokevirtual #15                 // Method java/lang/StringBuilder.append:(Ljava/lang/String;)Ljava/lang/StringBuilder;
      66: aload         4
      68: invokevirtual #15                 // Method java/lang/StringBuilder.append:(Ljava/lang/String;)Ljava/lang/StringBuilder;
      71: invokevirtual #16                 // Method java/lang/StringBuilder.toString:()Ljava/lang/String;
      74: astore_2
      75: goto          35
      78: invokestatic  #17                 // Method java/lang/Thread.currentThread:()Ljava/lang/Thread;
      81: invokevirtual #18                 // Method java/lang/Thread.join:()V
      84: return
}
```

ä» 55 å¼€å§‹, ä¼šåˆ›å»ºä¸€ä¸ª StringBuilder, åœ¨æ‰§è¡Œå®Œ appendæ–¹æ³•å (63), ç»§ç»­å¾ªç¯ä» 15 å¼€å§‹æ‰§è¡Œ. 
å¾ªç¯ç»“æŸå, æœ€åè°ƒç”¨ toString()

ä» JDK6 å¼€å§‹, JVM å¯¹ String ä½¿ç”¨ "+", åšäº†ä¼˜åŒ–, æ¯æ¬¡ä½¿ç”¨ "+" æ“ä½œç¬¦æ—¶, ä¼š `new StringBuilder()`, ç„¶åä½¿ç”¨ `append` è¿›è¡Œæ‹¼æ¥.

å› æ­¤åœ¨ JDK5 ä¹‹å, å¾ªç¯å¤–å­—ç¬¦ä¸²æ‹¼æ¥å¯ä»¥ç›´æ¥ä½¿ç”¨ String çš„ + æ“ä½œï¼Œæ²¡æœ‰å¿…è¦é€šè¿‡ StringBuilder è¿›è¡Œ append;
ä½†æ˜¯åœ¨å¾ªç¯å†…æ—¶, åº”è¯¥ä½¿ç”¨ StringBuilder, åŸå› ä¸Šé¢å·²ç»è¯´è¿‡äº†, ä¼šé€ æˆè¿‡å¤šçš„ StringBuilder å¯¹è±¡äº§ç”Ÿ, å¯èƒ½ä¼šäº§ç”Ÿé¢‘ç¹çš„ GC

## å­—ç¬¦ä¸²æ‹¼æ¥ + å’Œ concat çš„åŒºåˆ«

```java
public static void main(String[] args) {
    // example1
    String str1 = "s1";
    System.out.println(str1 + 100);//s1100
    System.out.println(100 + str1);//100s1

    String str2 = "s2";
    str2 = str2.concat("a").concat("bc");
    System.out.println(str2);//s2abc

    // example2
    String str3 = "s3";
    System.out.println(str3 + null);//s3null
    System.out.println(null + str3);//nulls3

    String str4 = null;
    System.out.println(str4.concat("a"));//NullPointerException
    System.out.println("a".concat(str4));//NullPointerException
}
```

**åŒºåˆ«**:

1. +å¯ä»¥æ˜¯å­—ç¬¦ä¸²æˆ–è€…æ•°å­—åŠå…¶ä»–åŸºæœ¬ç±»å‹æ•°æ®ï¼Œè€Œconcatåªèƒ½æ¥æ”¶å­—ç¬¦ä¸²ã€‚
2. +å·¦å³å¯ä»¥ä¸ºnullï¼Œconcatä¸ºä¼šç©ºæŒ‡é’ˆã€‚
3. å¦‚æœæ‹¼æ¥ç©ºå­—ç¬¦ä¸²ï¼Œconcatä¼šç¨å¿«ï¼Œåœ¨é€Ÿåº¦ä¸Šä¸¤è€…å¯ä»¥å¿½ç•¥ä¸è®¡ï¼Œå¦‚æœæ‹¼æ¥æ›´å¤šå­—ç¬¦ä¸²å»ºè®®ç”¨StringBuilderã€‚
4. ä»å­—èŠ‚ç æ¥çœ‹ + å·ç¼–è¯‘åå°±æ˜¯ä½¿ç”¨ äº†StringBuiler æ¥æ‹¼æ¥ï¼Œæ‰€ä»¥ä¸€è¡Œ + çš„è¯­å¥å°±ä¼šåˆ›å»ºä¸€ä¸ª StringBuilderï¼Œå¤šæ¡ + è¯­å¥å°±ä¼šåˆ›å»ºå¤šä¸ªï¼Œæ‰€ä»¥å»ºè®®åœ¨å¾ªç¯å†…æ‹¼æ¥æ—¶ç”¨ StringBuilder.

[ğŸ‘ˆ **ç›¸å…³é¢è¯•é¢˜**](./README.md#_54-ğŸ‘‰-string-å¯¹-çš„é‡è½½-å­—ç¬¦ä¸²æ‹¼æ¥çš„å‡ ç§æ–¹å¼å’ŒåŒºåˆ«)
